generic_search/__init__.py
generic_search/admin.py
generic_search/apps.py
generic_search/models.py
generic_search/tests.py
generic_search/urls.py
generic_search/views.py
generic_search/management/__init__.py
generic_search/management/commands/__init__.py
generic_search/management/commands/cleancrawlresults.py
generic_search/management/commands/generateindex.py
generic_search/management/commands/pagerank.py
generic_search/management/commands/startspider.py
generic_search/migrations/__init__.py
generic_search/searchbot/__init__.py
generic_search/searchbot/searchbot/__init__.py
generic_search/searchbot/searchbot/items.py
generic_search/searchbot/searchbot/middlewares.py
generic_search/searchbot/searchbot/pipelines.py
generic_search/searchbot/searchbot/settings.py
generic_search/searchbot/searchbot/spiders/__init__.py
generic_search/searchbot/searchbot/spiders/gammaspider.py
generic_search/static/bootstrap-5.1.3/css/bootstrap-grid.css
generic_search/static/bootstrap-5.1.3/css/bootstrap-grid.css.map
generic_search/static/bootstrap-5.1.3/css/bootstrap-grid.min.css
generic_search/static/bootstrap-5.1.3/css/bootstrap-grid.min.css.map
generic_search/static/bootstrap-5.1.3/css/bootstrap-grid.rtl.css
generic_search/static/bootstrap-5.1.3/css/bootstrap-grid.rtl.css.map
generic_search/static/bootstrap-5.1.3/css/bootstrap-grid.rtl.min.css
generic_search/static/bootstrap-5.1.3/css/bootstrap-grid.rtl.min.css.map
generic_search/static/bootstrap-5.1.3/css/bootstrap-reboot.css
generic_search/static/bootstrap-5.1.3/css/bootstrap-reboot.css.map
generic_search/static/bootstrap-5.1.3/css/bootstrap-reboot.min.css
generic_search/static/bootstrap-5.1.3/css/bootstrap-reboot.min.css.map
generic_search/static/bootstrap-5.1.3/css/bootstrap-reboot.rtl.css
generic_search/static/bootstrap-5.1.3/css/bootstrap-reboot.rtl.css.map
generic_search/static/bootstrap-5.1.3/css/bootstrap-reboot.rtl.min.css
generic_search/static/bootstrap-5.1.3/css/bootstrap-reboot.rtl.min.css.map
django_generic_search-2.1.0.dist-info/LICENSE
django_generic_search-2.1.0.dist-info/METADATA
django_generic_search-2.1.0.dist-info/WHEEL
django_generic_search-2.1.0.dist-info/top_level.txt
django_generic_search-2.1.0.dist-info/RECORD
