Metadata-Version: 2.1
Name: django-generic-search
Version: 2.1.0
Summary: A Django app to conduct generic search on a django web application.
Home-page: https://github.com/barakaVictor
Author: Victor Baraka Oyuga
Author-email: barakavictor62@gmail.com
License: BSD-3-Clause
Platform: UNKNOWN
Classifier: Environment :: Web Environment
Classifier: Framework :: Django
Classifier: Framework :: Django :: 4.0
Classifier: Intended Audience :: Developers
Classifier: License :: OSI Approved :: BSD License
Classifier: Operating System :: OS Independent
Classifier: Programming Language :: Python
Classifier: Programming Language :: Python :: 3
Classifier: Programming Language :: Python :: 3 :: Only
Classifier: Programming Language :: Python :: 3.8
Classifier: Programming Language :: Python :: 3.9
Classifier: Topic :: Internet :: WWW/HTTP
Classifier: Topic :: Internet :: WWW/HTTP :: Dynamic Content
Requires-Python: >=3.8
License-File: LICENSE
Requires-Dist: Django (>=4.0)
Requires-Dist: Scrapy (>=2.5.1)
Requires-Dist: nltk (>=3.6.7)
Requires-Dist: beautifulsoup4 (>=4.10.0)
Requires-Dist: numpy (>=1.22.1)
